ryxpress/__init__.py
ryxpress/copy_artifacts.py
ryxpress/cronista_helpers.py
ryxpress/garbage.py
ryxpress/init_proj.py
ryxpress/inspect_logs.py
ryxpress/plotting.py
ryxpress/r_runner.py
ryxpress/read_load.py
ryxpress/tracing.py
ryxpress-0.2.0.dist-info/licenses/LICENSE
ryxpress-0.2.0.dist-info/METADATA
ryxpress-0.2.0.dist-info/WHEEL
ryxpress-0.2.0.dist-info/top_level.txt
ryxpress-0.2.0.dist-info/RECORD
