Metadata-Version: 2.4
Name: ryxpress
Version: 0.2.0
Summary: Reproducible Analytical Pipelines with Nix
Author: Bruno Rodrigues
License: GPL-3.0-or-later
Project-URL: Homepage, https://github.com/b-rodrigues/ryxpress
Project-URL: Bug Tracker, https://github.com/b-rodrigues/ryxpress/issues
Keywords: nix,rap,pipelines,reproducibility
Classifier: Programming Language :: Python :: 3
Classifier: Operating System :: OS Independent
Requires-Python: >=3.8
License-File: LICENSE
Provides-Extra: dev
Requires-Dist: pytest>=7.0; extra == "dev"
Provides-Extra: cronista
Requires-Dist: cronista; extra == "cronista"
Dynamic: license-file
